snapshot_photo/__init__.py
snapshot_photo/date_format.py
snapshot_photo-0.0.3.dist-info/METADATA
snapshot_photo-0.0.3.dist-info/WHEEL
snapshot_photo-0.0.3.dist-info/top_level.txt
snapshot_photo-0.0.3.dist-info/RECORD
